[
    {
        "title": "MS",
        "name": "Paballo Thobei",
        "description": "Full Stack Intern",
        "available": false,
        "client": "DVT",
        "email": "pthobei@dvtsoftware.com",
        "github": "https://github.com/pthobei",
        "linkedin": "https://www.linkedin.com/in/paballo-thobei-2b532a27b?utm_source=share&utm_campaign=share_via&utm_content=profile&utm_medium=android_app",
        "techStack": ["HTML", "CSS", "JavaScript", "Java", "C#", "Python"],
        "softSkills": ["Active Listening", "Resilience", "Interpersonal Skills", "Teamwork"],
        "image": "./src/assets/Pabi.jpg",
        "Chat": "pthobei@jhb.dvt.co.za",
        "Phone": "+27 67 874 7814",
        "Location": "Johannesburg, South Africa",
        "Company": "DVT",
        "Department": "SA-DEVPS-S",
        "Role": "Full Stack Intern",
        "Institution": "WeThinkCode_",
        "Qualification": "NQF Level 5 - Systems Development",
        "Birthday": "2004-06-15"
    },
    
    {
        "title": "MR",
        "name": "Phemelo Makwatse",
        "description": "Full Stack Intern",
        "available": false,
        "client": "DVT",
        "email": "PMakwatse@dvtsoftware.com",
        "github": "https://github.com/PhimiTm",
        "linkedin": "https://www.linkedin.com/in/phemelo-makwatse?utm_source=share&utm_campaign=share_via&utm_content=profile&utm_medium=ios_app",
        "techStack": ["CSS", "JavaScript", "Java", "TypeScript", "SQL", "React"],
        "softSkills": ["Written Communication", "Teamwork", "Interpersonal Skills", "Delegation", "Learning Agility", "Critical Thinking"],
        "image": "./src/assets/Phemelo.jpg",
        "Chat": "pmakwatse@jhb.dvt.co.za",
        "Phone": "+27 83 200 4239",
        "Location": "Johannesburg, South Africa",
        "Company": "DVT",
        "Department": "SA-DEVPS-S",
        "Role": "Full Stack Intern",
        "Birthday": "2002-01-17"
    },
    
    {
        "title": "MR",
        "name": "Gomolemo Motlhamme",
        "description": "Full Stack Intern",
        "available": false,
        "client": "DVT",
        "email": "GMotlhamme@dvtsoftware.com",
        "github": "https://github.com/GomoAtDVT",
        "linkedin": "https://www.linkedin.com/in/mrgmotlhamme",
        "techStack": ["React",  "Kotlin", "JavaScript",  "SQL",  "Tailwind CSS"],
        "softSkills": ["Active Listening", "Teamwork", "Interpersonal Skills", "Prioritization", "Learning Agility", "Critical Thinking", "Creativity", "Punctuality"],
        "image": "./src/assets/Gomolemo.jpg",
        "Chat": "gmotlhamme@jhb.dvt.co.za",
        "Phone": "+27 79 185 6644",
        "Location": "Johannesburg, South Africa",
        "Company": "DVT",
        "Department": "SA-DEVPS-S",
        "Role": "Full Stack Intern",
        "Institution": "IIE Rosebank College",
        "Qualification": "Diploma in Information Technology for Software Development",
        "Birthday": "2001-09-21"
    },
    
    {
        "title": "MR",
        "name": "Adrian Majavu",
        "description": "Full Stack Intern",
        "available": false,
        "client": "DVT",
        "email": "AMajavu@dvtsoftware.com",
        "github": "https://github.com/Adrian19Jan",
        "linkedin": "https://www.linkedin.com/in/majavuadrian?utm_source=share&utm_campaign=share_via&utm_content=profile&utm_medium=ios_app",
        "techStack": ["HTML", "CSS", "JavaScript", "Java", "C++", "Kotlin", "C#"],
        "softSkills": ["Resilience", "Teamwork", "Interpersonal Skills", "Prioritization", "Learning Agility", "Critical Thinking"],
        "image": "./src/assets/Adrian.jpg",
        "Chat": "amajavu@jhb.dvt.co.za",
        "Phone": "+27 68 401 9098",
        "Location": "Johannesburg, South Africa",
        "Company": "DVT",
        "Department": "SA-DEVPS-S",
        "Role": "Full Stack Intern",
        "Birthday": "2000-01-19"
    },
    
    {
        "title": "MR",
        "name": "Njabulo Kukame",
        "description": "Full Stack Intern",
        "available": false,
        "client": "DVT",
        "email": "NKukame@dvtsoftware.com",
        "github": "https://github.com/NKukame",
        "linkedin": "https://www.linkedin.com/in/njabulo-kukame-05a223227?utm_source=share&utm_campaign=share_via&utm_content=profile&utm_medium=android_app",
        "techStack": ["React","Java", "CSS", "JavaScript",  "PHP", "SQL"],
        "softSkills": ["Active Listening", "Teamwork", "Interpersonal Skills", "Prioritization", "Learning Agility", "Critical Thinking", "Creativity", "Punctuality", "Resourcefulness", "Presentation Skills"],
        "image": "./src/assets/Njabulo-Kukame-Picture.jpg",
        "Chat": "nkukame@jhb.dvt.co.za",
        "Phone": "+27 61 543 0266",
        "Location": "Johannesburg, South Africa",
        "Company": "DVT",
        "Department": "SA-DEVPS-S",
        "Role": "Full Stack Intern",
        "Birthday": "2003-02-18"
    },
    
    {
        "title": "MR",
        "name": "Andile Mhlongo",
        "description": "Full Stack Intern",
        "available": false,
        "client": "DVT",
        "email": "AMhlongo@dvtsoftware.com",
        "github": "https://github.com/amhlongo-dvt",
        "linkedin": "https://www.linkedin.com/in/andile-mhlongo-a025a5b1/",
        "techStack": ["HTML", "CSS", "JavaScript", "Java", "C#", "TypeScript"],
        "softSkills": ["Active Listening", "Teamwork", "Interpersonal Skills", "Prioritization", "Learning Agility", "Critical Thinking", "Creativity", "Punctuality", "Resourcefulness"],
        "image": "./src/assets/Andile.jpg",
        "Chat": "amhlongo@jhb.dvt.co.za",
        "Phone": "+27 76 275 2913",
        "Location": "Johannesburg, South Africa",
        "Company": "DVT",
        "Department": "SA-DEVPS-S",
        "Role": "Full Stack Intern",
        "Institution": "WeThinkCode_",
        "Qualification": "NQF Level 5 - Systems Development",
        "Birthday": "1996-04-19"
    },
    
    {
        "title": "MR",
        "name": "Thabane Ngobe",
        "description": "Full Stack Intern",
        "available": false,
        "client": "DVT",
        "email": "TNgobe@dvtsoftware.com",
        "github": "https://github.com/Ngobe-Thabane",
        "linkedin": "https://www.linkedin.com/in/thabane-ngobe-thabanengobe?utm_source=share&utm_campaign=share_via&utm_content=profile&utm_medium=android_app",
        "techStack": ["HTML", "CSS", "JavaScript", "Java", "Python", "C"],
        "softSkills": ["Active Listening", "Teamwork", "Interpersonal Skills", "Prioritization", "Learning Agility", "Critical Thinking", "Creativity", "Punctuality", "Resourcefulness"],
        "image": "./src/assets/Thabane.jpeg",
        "Chat": "tngobe@jhb.dvt.co.za",
        "Phone": "+27 79 032 4941",
        "Location": "Johannesburg, South Africa",
        "Company": "DVT",
        "Department": "SA-DEVPS-S",
        "Role": "Full Stack Intern",
        "Institution": "WeThinkCode_",
        "Qualification": "NQF Level 5 - Systems Development",
        "Birthday": "2002-10-06"
    },
    
    {
        "title": "MS",
        "name": "Remow Rammekwa",
        "description": "Full Stack Intern",
        "available": false,
        "client": "DVT",
        "email": "RRammekwa@dvtsoftware.com",
        "github": "https://github.com/REMOW-web",
        "linkedin": "https://www.linkedin.com/in/remoneilwe-rammekwa-525571270?utm_source=share&utm_campaign=share_via&utm_content=profile&utm_medium=ios_app",
        "techStack": ["HTML", "JavaScript", "Java", "React", "Tailwind CSS"],
        "softSkills": ["Teamwork", "Interpersonal Skills", "Prioritization", "Learning Agility", "Critical Thinking", "Creativity", "Punctuality", "Resilience", "Presentation Skills"],
        "image": "./src/assets/Remo.jpg",
        "Chat": "rrammekwa@jhb.dvt.co.za",
        "Phone": "+27 84 824 3884",
        "Location": "Johannesburg, South Africa",
        "Company": "DVT",
        "Department": "SA-DEVPS-S",
        "Role": "Full Stack Intern",
        "Institution": "Vaal University of Technology",
        "Qualification": "Diploma in Information Technology",
        "Birthday": "2003-03-15"
    },
    

    {
        "title": "MR",
        "name": "Dylan Fernandes",
        "description": "UI/UX Intern",
        "available": false,
        "client": "DVT",
        "email": "DFernandes@dvtsoftware.com",
        "github": "Github Username",
        "linkedin": "https://www.linkedin.com/in/dylan-fernandes-615996345/",
        "techStack": ["Figma"],
        "softSkills": ["Active Listening", "Teamwork", "Interpersonal Skills", "Learning Agility", "Critical Thinking", "Creativity", "Resilience", "Decision Making", "Conflict Resolution"],
        "image": "./src/assets/Dylan.jpg",
        "Chat": "dfernades@jhb.dvt.co.za",
        "Phone": "+27 83 642 1211",
        "Location": "Johannesburg, South Africa",
        "Company": "DVT",
        "Department": "SA-DEVPS-S",
        "Role": "Full Stack Intern",
        "Institution": "University of Johannesburg",
        "Qualification": "MA(Arch) - Architecture",
        "Birthday": "1995-09-25"
    }

]